CHANGELOG.md
LICENSE
README.md
script_master_ui/__init__.py
script_master_ui/__main__.py
script_master_ui/cli.py
script_master_ui/const.py
script_master_ui/exceptions.py
script_master_ui/main.py
script_master_ui/routers/__init__.py
script_master_ui/routers/notebook.py
script_master_ui/routers/task.py
script_master_ui/routers/variable.py
script_master_ui/settings.py
script_master_ui/templates/base.html
script_master_ui/templates/footer.html
script_master_ui/templates/header.html
script_master_ui/templates/includes/global-style.html
script_master_ui/templates/navbar.html
script_master_ui/templates/pages/create-variable.html
script_master_ui/templates/pages/create.html
script_master_ui/templates/pages/detailed.html
script_master_ui/templates/pages/edit.html
script_master_ui/templates/pages/log.html
script_master_ui/templates/pages/notebooks.html
script_master_ui/templates/pages/tasks.html
script_master_ui/templates/pages/variables.html
script_master_ui/templates/pages/wrapper-detailed.html
script_master_ui/templates/pages/wrapper-editor.html
script_master_ui/templates/pages/wrapper-yaml-editor.html
script_master_ui/templates/pages/wrapper.html
script_master_ui/utils.py
script_master_ui-0.0.1.dist-info/entry_points.txt
script_master_ui-0.0.1.dist-info/LICENSE
script_master_ui-0.0.1.dist-info/WHEEL
script_master_ui-0.0.1.dist-info/METADATA
script_master_ui-0.0.1.dist-info/RECORD
