Metadata-Version: 2.1
Name: script-master-ui
Version: 0.0.1
Summary: 
Home-page: https://github.com/pavelmaksimov/script-master-ui
License: Apache-2.0
Author: Pavel Maksimov
Author-email: vur21@ya.ru
Requires-Python: >=3.10,<4.0
Classifier: License :: OSI Approved :: Apache Software License
Classifier: Programming Language :: Python :: 3
Classifier: Programming Language :: Python :: 3.10
Classifier: Programming Language :: Python :: 3.11
Requires-Dist: PyYAML (>=6.0,<7.0)
Requires-Dist: confz (>=1.8,<2.0)
Requires-Dist: fastapi (>=0.88,<0.89)
Requires-Dist: pydantic (>=1.9.0,<2.0.0)
Requires-Dist: script-master-helper (>=0.0.2,<0.0.3)
Requires-Dist: typer (>=0.7.0,<0.8.0)
Requires-Dist: uvicorn[standart] (>=0.20.0,<0.21.0)
